DHT11/__init__.py
include_beer_DHT11-1.0.2.dist-info/LICENSE
include_beer_DHT11-1.0.2.dist-info/METADATA
include_beer_DHT11-1.0.2.dist-info/WHEEL
include_beer_DHT11-1.0.2.dist-info/top_level.txt
include_beer_DHT11-1.0.2.dist-info/RECORD
